{
  "type": "list_card",
  "cells": [
    {
      "type": "text_cell_view",
      "content": {
        "text": "Пожалуйста, проверьте, верно ли я всё записал?",
        "typeface": "headline3",
        "text_color": "brand"
      }
    },
    {
      "type": "left_right_cell_view",
      "paddings": {
        "top": "6x",
        "bottom": "6x"
      },
      "divider": {
        "style": "default",
        "size": "d2"
      },
      "actions": [
        {
          "type": "text",
          "text": "send nudes"
        }
      ],
      "left": {
        "type": "simple_left_view",
        "texts": {
          "title": {
            "text": "12312321123",
            "typeface": "body1",
            "text_color": "default",
            "max_lines": 0
          }
        }
      },
      "right": {
        "type": "simple_left_view",
        "texts": {
          "title": {
            "text": "assas",
            "typeface": "body1",
            "text_color": "default",
            "max_lines": 0
          }
        }
      }
    }
  ]
}

